columbus/__init__.py
columbus/framework/__init__.py
columbus/framework/application.py
columbus/framework/constants.py
columbus/framework/requests.py
columbus/framework/utils.py
columbus/framework/validators.py
columbus/main.py
columbus/run.py
columbus/start.py
columbus-0.1.9.dist-info/entry_points.txt
columbus-0.1.9.dist-info/WHEEL
columbus-0.1.9.dist-info/METADATA
columbus-0.1.9.dist-info/RECORD
